MANIFEST.in
README.md
contributors.mkd
data_fabfile.py
fabfile.py
setup.py
cloudbio/__init__.py
cloudbio/cloudbiolinux.py
cloudbio/cloudman.py
cloudbio/distribution.py
cloudbio/utils.py
cloudbio/biodata/__init__.py
cloudbio/biodata/dbsnp.py
cloudbio/biodata/genomes.py
cloudbio/biodata/rnaseq.py
cloudbio/custom/__init__.py
cloudbio/custom/bio_general.py
cloudbio/custom/bio_nextgen.py
cloudbio/custom/cloudman.py
cloudbio/custom/distributed.py
cloudbio/custom/galaxy.py
cloudbio/custom/java.py
cloudbio/custom/phylogeny.py
cloudbio/custom/python.py
cloudbio/custom/shared.py
cloudbio/custom/system.py
cloudbio/custom/vcr.py
cloudbio/edition/__init__.py
cloudbio/edition/base.py
cloudbio/flavor/__init__.py
cloudbio/flavor/config.py
cloudbio/galaxy/__init__.py
cloudbio/galaxy/applications.py
cloudbio/galaxy/r.py
cloudbio/galaxy/tools.py
cloudbio/galaxy/utils.py
cloudbio/package/__init__.py
cloudbio/package/deb.py
cloudbio/package/nix.py
cloudbio/package/rpm.py
cloudbio/package/shared.py
cloudbiolinux.egg-info/PKG-INFO
cloudbiolinux.egg-info/SOURCES.txt
cloudbiolinux.egg-info/dependency_links.txt
cloudbiolinux.egg-info/requires.txt
cloudbiolinux.egg-info/top_level.txt
config/README.md
config/biodata.yaml
config/custom.yaml
config/fabricrc.txt
config/haskell-libs.yaml
config/main.yaml
config/packages-debian.yaml
config/packages-nix.yaml
config/packages-scientificlinux.yaml
config/packages-yum.yaml
config/packages.yaml
config/perl-libs.yaml
config/python-libs.yaml
config/r-libs.yaml
config/ruby-libs.yaml
contrib/__init__.py
contrib/flavor/__init__.py
contrib/flavor/boinc/__init__.py
contrib/flavor/boinc/boincflavor.py
contrib/flavor/phylogeny/__init__.py
contrib/flavor/phylogeny/phylogenyflavor.py
contrib/flavor/pjotrp/__init__.py
contrib/flavor/pjotrp/biotest/__init__.py
contrib/flavor/pjotrp/biotest/biotestflavor.py
contrib/flavor/seal/__init__.py
contrib/flavor/seal/sealflavor.py
doc/hacking.md
doc/linux_kvm.md
doc/private_cloud.md
doc/remote_gui.md
doc/virtualbox.md
installed_files/bash_login
installed_files/ec2autorun.py
installed_files/galaxy_default.template
installed_files/galaxy_init
installed_files/nginx.conf.template
installed_files/nginx_init
