Metadata-Version: 1.0
Name: cloudbiolinux
Version: 0.3a
Summary: configure virtual (or real) machines with tools for biological analyses
Home-page: http://cloudbiolinux.org
Author: Brad Chapman
Author-email: chapmanb@50mail.com
License: MIT
Platform: UNKNOWN
